ufma_scrapper/__init__.py
ufma_scrapper/acervobiblioteca.py
ufma_scrapper/curso.py
ufma_scrapper/docente.py
ufma_scrapper/subunidade.py
ufma_scrapper/unidade.py
ufma_scrapper-0.0.11.dist-info/LICENSE
ufma_scrapper-0.0.11.dist-info/METADATA
ufma_scrapper-0.0.11.dist-info/WHEEL
ufma_scrapper-0.0.11.dist-info/top_level.txt
ufma_scrapper-0.0.11.dist-info/RECORD
