Metadata-Version: 2.1
Name: ufma-scrapper
Version: 0.0.11
Summary: TYPE YOUR DESCRIPTION HERE
Home-page: https://github.com/inovacampus/ufma_scrapper
Author: Sérgio Souza Costa
Author-email: profsergiocosta@gmail.com
License: MIT
Keywords: SOME,MEANINGFULL,KEYWORDS
Platform: UNKNOWN
Classifier: Development Status :: 3 - Alpha
Classifier: Intended Audience :: Developers
Classifier: Topic :: Software Development :: Build Tools
Classifier: License :: OSI Approved :: MIT License
Classifier: Programming Language :: Python :: 3
Classifier: Programming Language :: Python :: 3.4
Classifier: Programming Language :: Python :: 3.5
Classifier: Programming Language :: Python :: 3.6
Requires-Dist: requests
Requires-Dist: bs4
Requires-Dist: lxml
Requires-Dist: unidecode
Requires-Dist: pymarc
